flask_queryinspect
